.gitignore
CHANGES.txt
README.rst
setup.cfg
setup.py
limone/__init__.py
limone/tests.py
limone.egg-info/PKG-INFO
limone.egg-info/SOURCES.txt
limone.egg-info/dependency_links.txt
limone.egg-info/entry_points.txt
limone.egg-info/not-zip-safe
limone.egg-info/requires.txt
limone.egg-info/top_level.txt