Metadata-Version: 1.0
Name: limone
Version: 0.1a5
Summary: Content type system based on colander schemas.
Home-page: http://pylonsproject.org
Author: Chris Rossi, Archimedean Company
Author-email: pylons-devel@googlegroups.com
License: BSD-derived (http://www.repoze.org/LICENSE.txt)
Platform: UNKNOWN
Classifier: Intended Audience :: Developers
Classifier: Programming Language :: Python
Classifier: Framework :: Pylons
Classifier: License :: Repoze Public License
